[
    {
        "dist": 9.8,
        "geo_source": "raw",
        "felt": "1",
        "time_now": "2016-07-12T02:11:57",
        "exttable": "extended_2016",
        "subid": 4360534,
        "cityid": 73010,
        "region": "cus",
        "longitude": -97.6581,
        "orig_id": "unknown",
        "citydb": "zip_2008",
        "eventid": "us100062t7",
        "usertime": "9:08",
        "latitude": 35.1378,
        "user_cdi": "2.0"
    },
    {
        "shelf": "0 rattled_slightly",
        "picture": "0",
        "reaction": "1",
        "time_now": "2016-07-12T02:13:46",
        "heavy_appliance": "0",
        "sway": "0",
        "subid": 4360535,
        "motion": "3",
        "asleep": "no",
        "region": "cus",
        "longitude": -97.6512,
        "other_felt": "5",
        "creak": "1 slight",
        "latitude": 35.1672,
        "eventid": "us100062t7",
        "dist": 12.5,
        "felt": "1",
        "cityid": 73010,
        "furniture": "0",
        "orig_id": "unknown",
        "exttable": "extended_2016",
        "citydb": "zip_2008",
        "usertime": "7/11/2016 9:08 PM",
        "geo_source": "raw",
        "user_cdi": "3.1"
    },
    {
        "shelf": "0 rattled_slightly",
        "picture": "0",
        "reaction": "2",
        "time_now": "2016-07-12T02:14:35",
        "heavy_appliance": "0",
        "sway": "0",
        "subid": 4360536,
        "motion": "1",
        "asleep": "no",
        "stand": "0",
        "citydb": "zip_2008",
        "longitude": -97.6606,
        "other_felt": "2",
        "creak": "1 slight",
        "d_text": "_none",
        "latitude": 35.1387,
        "eventid": "us100062t7",
        "dist": 9.9,
        "felt": "1",
        "walls": "0",
        "cityid": 73010,
        "geo_source": "raw",
        "orig_id": "unknown",
        "exttable": "extended_2016",
        "region": "cus",
        "usertime": "5 minutes ago",
        "furniture": "0",
        "user_cdi": "2.0"
    },
    {
        "dist": 5.6,
        "geo_source": "raw",
        "felt": "1",
        "time_now": "2016-07-12T02:14:49",
        "exttable": "extended_2016",
        "subid": 4360537,
        "cityid": 73010,
        "region": "cus",
        "longitude": -97.5773,
        "orig_id": "unknown",
        "citydb": "zip_2008",
        "eventid": "us100062t7",
        "usertime": "9:10 pm central time",
        "latitude": 35.017,
        "user_cdi": "2.0"
    },
    {
        "shelf": "0",
        "picture": "1 did_not_fall",
        "reaction": "1",
        "time_now": "2016-07-12T02:14:55",
        "heavy_appliance": "0",
        "sway": "0",
        "subid": 4360538,
        "motion": "2",
        "asleep": "no",
        "stand": "0",
        "citydb": "zip_2008",
        "longitude": -97.6616,
        "other_felt": "5",
        "creak": "1 slight",
        "d_text": "_none",
        "latitude": 35.0306,
        "eventid": "us100062t7",
        "dist": 5.7,
        "felt": "1",
        "walls": "0",
        "cityid": 73010,
        "geo_source": "raw",
        "orig_id": "unknown",
        "exttable": "extended_2016",
        "region": "cus",
        "usertime": "906 pm",
        "furniture": "0",
        "user_cdi": "3.4"
    },
    {
        "dist": 8.9,
        "geo_source": "raw",
        "felt": "1",
        "time_now": "2016-07-12T02:16:07",
        "exttable": "extended_2016",
        "subid": 4360539,
        "cityid": 73093,
        "region": "cus",
        "longitude": -97.5205,
        "orig_id": "unknown",
        "citydb": "zip_2008",
        "eventid": "us100062t7",
        "usertime": "9:10",
        "latitude": 35.0925,
        "user_cdi": "2.0"
    },
    {
        "shelf": "0 rattled_loudly",
        "reaction": "2",
        "time_now": "2016-07-12T02:16:48",
        "heavy_appliance": "0",
        "sway": "0",
        "subid": 4360540,
        "motion": "3",
        "asleep": "no",
        "citydb": "zip_2008",
        "longitude": -97.6298,
        "other_felt": "4",
        "creak": "1 loud",
        "d_text": "_none",
        "latitude": 35.0334,
        "eventid": "us100062t7",
        "dist": 3.5,
        "felt": "1",
        "walls": "0",
        "cityid": 73010,
        "geo_source": "raw",
        "orig_id": "unknown",
        "exttable": "extended_2016",
        "region": "cus",
        "usertime": "9:10 pm 7/11/16",
        "furniture": "0",
        "user_cdi": "3.4"
    },
    {
        "shelf": "0 rattled_loudly",
        "reaction": "2",
        "time_now": "2016-07-12T02:18:19",
        "heavy_appliance": "0",
        "sway": "0",
        "subid": 4360541,
        "motion": "2",
        "asleep": "no",
        "stand": "0",
        "region": "cus",
        "longitude": -97.6198,
        "creak": "1 loud",
        "latitude": 35.1342,
        "eventid": "us100062t7",
        "dist": 8.3,
        "felt": "1",
        "cityid": 73010,
        "furniture": "0",
        "orig_id": "unknown",
        "exttable": "extended_2016",
        "citydb": "zip_2008",
        "usertime": "0910 pm",
        "geo_source": "raw",
        "user_cdi": "3.1"
    },
    {
        "shelf": "0 rattled_slightly",
        "reaction": "2",
        "time_now": "2016-07-12T02:18:46",
        "heavy_appliance": "0",
        "sway": "0",
        "subid": 4360542,
        "motion": "3",
        "asleep": "no",
        "stand": "0",
        "region": "cus",
        "longitude": -97.6749,
        "other_felt": "3",
        "creak": "1 loud",
        "d_text": "_none",
        "latitude": 35.0743,
        "eventid": "us100062t7",
        "dist": 6.2,
        "felt": "1",
        "cityid": 73004,
        "geo_source": "raw",
        "orig_id": "unknown",
        "exttable": "extended_2016",
        "citydb": "zip_2008",
        "usertime": "7/11/2016, 9:13 pm CST",
        "furniture": "0",
        "user_cdi": "2.9"
    },
    {
        "shelf": "0",
        "picture": "0",
        "reaction": "3",
        "time_now": "2016-07-12T02:20:51",
        "heavy_appliance": "0",
        "sway": "0",
        "subid": 4360543,
        "motion": "3",
        "asleep": "no",
        "region": "cus",
        "longitude": -97.6435,
        "other_felt": "5",
        "creak": "1 slight",
        "latitude": 35.1373,
        "eventid": "us100062t7",
        "dist": 9.2,
        "felt": "1",
        "cityid": 73010,
        "furniture": "0",
        "orig_id": "unknown",
        "exttable": "extended_2016",
        "citydb": "zip_2008",
        "usertime": "9:08pm cst",
        "geo_source": "raw",
        "user_cdi": "3.8"
    },
    {
        "shelf": "0 rattled_slightly",
        "picture": "0",
        "reaction": "1",
        "time_now": "2016-07-12T02:21:10",
        "heavy_appliance": "0",
        "sway": "0",
        "subid": 4360544,
        "motion": "3",
        "asleep": "no",
        "stand": "0",
        "region": "cus",
        "longitude": -97.6465,
        "creak": "1 loud",
        "d_text": "_none",
        "latitude": 35.1379,
        "eventid": "us100062t7",
        "dist": 9.3,
        "felt": "1",
        "cityid": 73010,
        "geo_source": "raw",
        "orig_id": "unknown",
        "exttable": "extended_2016",
        "citydb": "zip_2008",
        "usertime": "7/11/2016 9:15pm",
        "furniture": "0",
        "user_cdi": "3.1"
    },
    {
        "dist": 4.6,
        "geo_source": "raw",
        "felt": "1",
        "time_now": "2016-07-12T02:21:42",
        "exttable": "extended_2016",
        "subid": 4360545,
        "cityid": 73010,
        "region": "cus",
        "longitude": -97.622,
        "orig_id": "unknown",
        "citydb": "zip_2008",
        "eventid": "us100062t7",
        "usertime": "9:10pm",
        "latitude": 35.1001,
        "user_cdi": "2.0"
    },
    {
        "shelf": "0 rattled_slightly",
        "picture": "0",
        "reaction": "1",
        "time_now": "2016-07-12T02:22:11",
        "heavy_appliance": "0",
        "sway": "1 slight",
        "subid": 4360546,
        "motion": "1",
        "asleep": "no",
        "stand": "0",
        "citydb": "zip_2008",
        "longitude": -97.6954,
        "creak": "1 slight",
        "d_text": "_none",
        "latitude": 35.0954,
        "eventid": "us100062t7",
        "dist": 8.8,
        "felt": "1",
        "walls": "0",
        "cityid": 73004,
        "geo_source": "raw",
        "orig_id": "unknown",
        "exttable": "extended_2016",
        "region": "cus",
        "usertime": "9 08 pm",
        "furniture": "0",
        "user_cdi": "2.2"
    },
    {
        "dist": 9.3,
        "geo_source": "raw",
        "felt": "1",
        "time_now": "2016-07-12T02:23:27",
        "exttable": "extended_2016",
        "subid": 4360547,
        "cityid": 73010,
        "region": "cus",
        "longitude": -97.6355,
        "orig_id": "unknown",
        "citydb": "zip_2008",
        "eventid": "us100062t7",
        "usertime": "Around 9:00 pm",
        "latitude": 35.1403,
        "user_cdi": "2.0"
    },
    {
        "dist": 9.8,
        "geo_source": "raw",
        "felt": "1",
        "time_now": "2016-07-12T02:23:35",
        "exttable": "extended_2016",
        "subid": 4360548,
        "asleep": "no",
        "cityid": 73010,
        "region": "cus",
        "longitude": -97.6581,
        "orig_id": "unknown",
        "citydb": "zip_2008",
        "eventid": "us100062t7",
        "usertime": "9:18",
        "latitude": 35.1378,
        "user_cdi": "2.0"
    },
    {
        "shelf": "0 rattled_slightly",
        "picture": "0",
        "reaction": "2",
        "time_now": "2016-07-12T02:26:17",
        "heavy_appliance": "0",
        "sway": "0",
        "subid": 4360549,
        "motion": "2",
        "asleep": "no",
        "stand": "0",
        "citydb": "zip_2008",
        "longitude": -97.6582,
        "creak": "1 slight",
        "d_text": "_none",
        "latitude": 35.1385,
        "eventid": "us100062t7",
        "dist": 9.8,
        "felt": "1",
        "walls": "0",
        "cityid": 73010,
        "geo_source": "raw",
        "orig_id": "unknown",
        "exttable": "extended_2016",
        "region": "cus",
        "usertime": "10 minutes ago",
        "furniture": "0",
        "user_cdi": "3.1"
    },
    {
        "shelf": "0",
        "picture": "0",
        "reaction": "1",
        "time_now": "2016-07-12T02:26:22",
        "heavy_appliance": "0",
        "sway": "0",
        "subid": 4360550,
        "motion": "1",
        "asleep": "woke",
        "stand": "0",
        "citydb": "zip_2008",
        "longitude": -97.6781,
        "other_felt": "5",
        "d_text": "_none",
        "latitude": 35.0896,
        "eventid": "us100062t7",
        "dist": 7.1,
        "felt": "1",
        "walls": "0",
        "cityid": 73004,
        "geo_source": "raw",
        "orig_id": "unknown",
        "exttable": "extended_2016",
        "region": "cus",
        "usertime": "5 mins ago",
        "furniture": "0",
        "user_cdi": "2.2"
    },
    {
        "dist": 11.3,
        "geo_source": "raw",
        "felt": "1",
        "time_now": "2016-07-12T02:27:01",
        "exttable": "extended_2016",
        "subid": 4360551,
        "cityid": 73010,
        "region": "cus",
        "longitude": -97.6478,
        "orig_id": "unknown",
        "citydb": "zip_2008",
        "eventid": "us100062t7",
        "usertime": "7/11/2016 10 minutes ago",
        "latitude": 35.1566,
        "user_cdi": "2.0"
    },
    {
        "dist": 10.1,
        "geo_source": "raw",
        "felt": "1",
        "time_now": "2016-07-12T02:29:14",
        "exttable": "extended_2016",
        "subid": 4360552,
        "cityid": 73010,
        "region": "cus",
        "longitude": -97.6737,
        "orig_id": "unknown",
        "citydb": "zip_2008",
        "eventid": "us100062t7",
        "usertime": "7/11/2016 9:20 pm",
        "latitude": 35.1333,
        "user_cdi": "2.0"
    },
    {
        "shelf": "0 rattled_slightly",
        "picture": "0",
        "reaction": "1",
        "time_now": "2016-07-12T02:29:25",
        "heavy_appliance": "0",
        "sway": "1 slight",
        "subid": 4360553,
        "motion": "3",
        "asleep": "no",
        "stand": "0",
        "citydb": "zip_2008",
        "longitude": -97.6232,
        "other_felt": "4",
        "creak": "1 loud",
        "d_text": "_none",
        "latitude": 35.1344,
        "eventid": "us100062t7",
        "dist": 8.4,
        "felt": "1",
        "walls": "0",
        "cityid": 73010,
        "geo_source": "raw",
        "orig_id": "unknown",
        "exttable": "extended_2016",
        "region": "cus",
        "usertime": "5 minutes ago",
        "furniture": "0",
        "user_cdi": "3.1"
    },
    {
        "dist": 7.8,
        "reaction": "2",
        "felt": "1",
        "time_now": "2016-07-12T02:29:37",
        "exttable": "extended_2016",
        "subid": 4360554,
        "motion": "2",
        "asleep": "no",
        "cityid": 73010,
        "region": "cus",
        "orig_id": "unknown",
        "other_felt": "5",
        "geo_source": "raw",
        "citydb": "zip_2008",
        "longitude": -97.6592,
        "eventid": "us100062t7",
        "usertime": "Tue, 12 Jul 2016 02:08:20 GMT",
        "latitude": 35.1165,
        "user_cdi": "3.1"
    },
    {
        "shelf": "0 rattled_slightly",
        "picture": "1 did_not_fall",
        "reaction": "2",
        "time_now": "2016-07-12T02:29:40",
        "heavy_appliance": "0",
        "sway": "0",
        "subid": 4360555,
        "motion": "2",
        "asleep": "no",
        "stand": "0",
        "citydb": "zip_2008",
        "longitude": -97.3611,
        "other_felt": "3",
        "creak": "1 slight",
        "d_text": "_none",
        "latitude": 35.0137,
        "eventid": "us100062t7",
        "dist": 23.2,
        "felt": "1",
        "walls": "0",
        "cityid": 73080,
        "geo_source": "raw",
        "orig_id": "unknown",
        "exttable": "extended_2016",
        "region": "cus",
        "usertime": "9:05 p.m 7/11/2016",
        "furniture": "0",
        "user_cdi": "3.3"
    },
    {
        "dist": 7.1,
        "geo_source": "raw",
        "felt": "1",
        "time_now": "2016-07-12T02:29:54",
        "exttable": "extended_2016",
        "subid": 4360556,
        "cityid": 73010,
        "region": "cus",
        "longitude": -97.6586,
        "orig_id": "unknown",
        "citydb": "zip_2008",
        "eventid": "us100062t7",
        "usertime": "15",
        "latitude": 35.0102,
        "user_cdi": "2.0"
    },
    {
        "shelf": "0 rattled_slightly",
        "picture": "1 did_not_fall",
        "time_now": "2016-07-12T02:34:53",
        "heavy_appliance": "0",
        "sway": "1 slight",
        "subid": 4360559,
        "motion": "4",
        "asleep": "no",
        "region": "cus",
        "longitude": -97.6765,
        "other_felt": "5",
        "creak": "1 loud",
        "d_text": "_none",
        "latitude": 35.1758,
        "eventid": "us100062t7",
        "dist": 14.3,
        "felt": "1",
        "cityid": 73010,
        "furniture": "0",
        "orig_id": "unknown",
        "exttable": "extended_2016",
        "citydb": "zip_2008",
        "usertime": "9:09 pm",
        "geo_source": "raw",
        "user_cdi": "3.8"
    },
    {
        "shelf": "0 rattled_loudly",
        "picture": "0",
        "reaction": "3",
        "time_now": "2016-07-12T02:40:40",
        "heavy_appliance": "0",
        "sway": "0",
        "subid": 4360561,
        "motion": "3",
        "asleep": "no",
        "stand": "0",
        "citydb": "zip_2008",
        "longitude": -97.6777,
        "other_felt": "4",
        "creak": "1 loud",
        "d_text": "_none",
        "latitude": 35.1272,
        "eventid": "us100062t7",
        "dist": 9.7,
        "felt": "1",
        "walls": "0",
        "cityid": 73010,
        "geo_source": "raw",
        "orig_id": "unknown",
        "exttable": "extended_2016",
        "region": "cus",
        "usertime": "Tue, 12 Jul 2016 02:08:20 GMT",
        "furniture": "0",
        "user_cdi": "3.8"
    },
    {
        "shelf": "0",
        "picture": "0",
        "reaction": "3",
        "time_now": "2016-07-12T02:40:59",
        "heavy_appliance": "0",
        "sway": "0",
        "subid": 4360562,
        "motion": "2",
        "asleep": "no",
        "stand": "0",
        "citydb": "zip_2008",
        "longitude": -97.6274,
        "creak": "1 loud",
        "d_text": "_none",
        "latitude": 35.0755,
        "eventid": "us100062t7",
        "dist": 2.4,
        "felt": "1",
        "walls": "0",
        "cityid": 73010,
        "geo_source": "raw",
        "orig_id": "unknown",
        "exttable": "extended_2016",
        "region": "cus",
        "usertime": "Tue, 12 Jul 2016 02:08:20 GMT",
        "furniture": "0",
        "user_cdi": "3.4"
    },
    {
        "shelf": "0",
        "picture": "0",
        "reaction": "2",
        "time_now": "2016-07-12T02:42:40",
        "heavy_appliance": "0",
        "sway": "0",
        "subid": 4360563,
        "motion": "4",
        "asleep": "no",
        "stand": "0",
        "citydb": "zip_2008",
        "longitude": -97.6719,
        "other_felt": "5",
        "creak": "1 loud",
        "d_text": "_none",
        "latitude": 35.1357,
        "eventid": "us100062t7",
        "dist": 10.2,
        "felt": "1",
        "walls": "0",
        "cityid": 73010,
        "geo_source": "raw",
        "orig_id": "unknown",
        "exttable": "extended_2016",
        "region": "cus",
        "usertime": "Tue, 12 Jul 2016 02:08:20 GMT",
        "furniture": "0",
        "user_cdi": "3.8"
    },
    {
        "shelf": "0",
        "picture": "0",
        "reaction": "1",
        "time_now": "2016-07-12T02:46:32",
        "heavy_appliance": "0",
        "sway": "0",
        "subid": 4360564,
        "motion": "1",
        "asleep": "no",
        "stand": "0",
        "citydb": "zip_2008",
        "longitude": -97.6581,
        "other_felt": "4",
        "d_text": "_none",
        "latitude": 35.1378,
        "eventid": "us100062t7",
        "dist": 9.8,
        "felt": "1",
        "walls": "0",
        "cityid": 73010,
        "geo_source": "raw",
        "orig_id": "unknown",
        "exttable": "extended_2016",
        "region": "cus",
        "usertime": "Tue, 12 Jul 2016 02:08:20 GMT",
        "furniture": "0",
        "user_cdi": "2.2"
    },
    {
        "shelf": "0 rattled_loudly",
        "reaction": "4",
        "time_now": "2016-07-12T02:47:44",
        "heavy_appliance": "0",
        "exttable": "extended_2016",
        "subid": 4360565,
        "asleep": "no",
        "region": "cus",
        "longitude": -97.6551,
        "creak": "1 loud",
        "d_text": "_none",
        "latitude": 35.0453,
        "eventid": "us100062t7",
        "dist": 4.4,
        "user_cdi": "4.3",
        "felt": "1",
        "cityid": 73010,
        "furniture": "0",
        "picture": "0",
        "motion": "4",
        "citydb": "zip_2008",
        "usertime": "Tue, 12 Jul 2016 02:08:20 GMT",
        "geo_source": "raw",
        "orig_id": "unknown"
    },
    {
        "dist": 10.6,
        "citydb": "zip_2008",
        "felt": "1",
        "time_now": "2016-07-12T02:47:47",
        "exttable": "extended_2016",
        "subid": 4360566,
        "asleep": "no",
        "cityid": 73010,
        "region": "cus",
        "orig_id": "unknown",
        "other_felt": "4",
        "geo_source": "raw",
        "user_cdi": "2.0",
        "eventid": "us100062t7",
        "usertime": "Tue, 12 Jul 2016 02:08:20 GMT",
        "latitude": 35.1484,
        "longitude": -97.6512
    },
    {
        "shelf": "0",
        "reaction": "3",
        "time_now": "2016-07-12T02:53:01",
        "heavy_appliance": "0",
        "exttable": "extended_2016",
        "subid": 4360570,
        "asleep": "no",
        "citydb": "zip_2008",
        "longitude": -97.6588,
        "d_text": "_none",
        "latitude": 35.0085,
        "eventid": "us100062t7",
        "dist": 7.3,
        "user_cdi": "3.8",
        "felt": "1",
        "walls": "0",
        "cityid": 73010,
        "furniture": "0",
        "picture": "0",
        "motion": "3",
        "region": "cus",
        "usertime": "Tue, 12 Jul 2016 02:08:20 GMT",
        "geo_source": "raw",
        "orig_id": "unknown"
    },
    {
        "dist": 20.1,
        "geo_source": "raw",
        "felt": "0",
        "time_now": "2016-07-12T03:06:25",
        "exttable": "extended_2016",
        "subid": 4360572,
        "cityid": 73072,
        "region": "cus",
        "longitude": -97.5157,
        "orig_id": "unknown",
        "citydb": "zip_2008",
        "eventid": "us100062t7",
        "usertime": "Tue, 12 Jul 2016 02:08:20 GMT",
        "latitude": 35.2237,
        "user_cdi": "1.0"
    },
    {
        "shelf": "0 rattled_slightly",
        "picture": "0",
        "reaction": "2",
        "time_now": "2016-07-12T03:06:29",
        "heavy_appliance": "0",
        "sway": "0",
        "subid": 4360573,
        "motion": "2",
        "asleep": "no",
        "stand": "0",
        "citydb": "zip_2008",
        "longitude": -97.6554,
        "other_felt": "4",
        "creak": "1 slight",
        "d_text": "_none",
        "latitude": 35.1411,
        "eventid": "us100062t7",
        "dist": 10.0,
        "felt": "1",
        "walls": "0",
        "cityid": 73010,
        "geo_source": "raw",
        "orig_id": "unknown",
        "exttable": "extended_2016",
        "region": "cus",
        "usertime": "Tue, 12 Jul 2016 02:08:20 GMT",
        "furniture": "0",
        "user_cdi": "3.1"
    }
]