[
    {
        "dist": 3.7,
        "geo_source": "raw",
        "felt": "1",
        "time_now": "2016-03-07T13:22:25",
        "exttable": "extended_2016",
        "subid": 4311287,
        "confidence": "3",
        "orig_id": "unknown",
        "cityid": 73034,
        "region": "cus",
        "user_cdi": "2.0",
        "version": "1.4",
        "citydb": "zip_2008",
        "eventid": "us10004vu6",
        "usertime": "1 minute ago",
        "latitude": 35.644,
        "longitude": -97.4259
    },
    {
        "dist": 4.5,
        "geo_source": "raw",
        "felt": "1",
        "time_now": "2016-03-07T13:23:52",
        "exttable": "extended_2016",
        "subid": 4311288,
        "confidence": "5",
        "orig_id": "unknown",
        "cityid": 73013,
        "region": "cus",
        "user_cdi": "2.0",
        "version": "1.4",
        "citydb": "zip_2008",
        "eventid": "us10004vu6",
        "usertime": "3/7/2016 7:22 AM",
        "latitude": 35.636,
        "longitude": -97.429
    },
    {
        "dist": 2.0,
        "geo_source": "raw",
        "citydb": "zip_2008",
        "reaction": "3",
        "felt": "1",
        "time_now": "2016-03-07T13:26:30",
        "exttable": "extended_2016",
        "subid": 4311289,
        "motion": "2",
        "confidence": "5",
        "cityid": 73007,
        "region": "cus",
        "orig_id": "unknown",
        "version": "1.4",
        "creak": "1 loud",
        "user_cdi": "3.4",
        "eventid": "us10004vu6",
        "usertime": "7:22am",
        "latitude": 35.6736,
        "longitude": -97.3757
    },
    {
        "reaction": "2",
        "time_now": "2016-03-07T13:38:22",
        "exttable": "extended_2016",
        "subid": 4311290,
        "motion": "2",
        "asleep": "no",
        "stand": "0",
        "region": "cus",
        "longitude": -97.4282,
        "other_felt": "5",
        "creak": "1 slight",
        "latitude": 35.6639,
        "eventid": "us10004vu6",
        "dist": 3.0,
        "felt": "1",
        "version": "1.4",
        "confidence": "4",
        "cityid": 73034,
        "orig_id": "unknown",
        "sway": "0",
        "citydb": "zip_2008",
        "usertime": "3/7/2016  7:21 a.m.",
        "geo_source": "raw",
        "user_cdi": "3.1"
    },
    {
        "shelf": "0",
        "picture": "0",
        "reaction": "1",
        "time_now": "2016-03-07T14:05:35",
        "heavy_appliance": "0",
        "exttable": "extended_2016",
        "subid": 4311294,
        "motion": "1",
        "asleep": "woke",
        "stand": "0",
        "citydb": "zip_2008",
        "longitude": -97.4303,
        "other_felt": "5",
        "creak": "1 slight",
        "latitude": 35.6469,
        "eventid": "us10004vu6",
        "dist": 3.8,
        "felt": "1",
        "version": "1.4",
        "walls": "0",
        "cityid": 73034,
        "confidence": "5",
        "geo_source": "raw",
        "user_cdi": "2.2",
        "sway": "0",
        "region": "cus",
        "usertime": "7:24am central 3/7/1",
        "furniture": "0",
        "orig_id": "unknown"
    },
    {
        "shelf": "0",
        "picture": "0",
        "reaction": "1",
        "time_now": "2016-03-07T20:28:54",
        "heavy_appliance": "0",
        "exttable": "extended_2016",
        "subid": 4311329,
        "motion": "1",
        "asleep": "no",
        "stand": "0",
        "citydb": "zip_2008",
        "longitude": -97.3912,
        "other_felt": "4",
        "creak": "1 slight",
        "d_text": "_none",
        "latitude": 35.6819,
        "eventid": "us10004vu6",
        "dist": 1.8,
        "felt": "1",
        "version": "1.4",
        "walls": "0",
        "cityid": 73034,
        "confidence": "4",
        "geo_source": "raw",
        "user_cdi": "2.2",
        "sway": "0",
        "region": "cus",
        "usertime": "1457356909",
        "furniture": "0",
        "orig_id": "us10004vu6"
    },
    {
        "dist": 5.1,
        "geo_source": "raw",
        "reaction": "1",
        "felt": "1",
        "time_now": "2016-03-07T21:18:49",
        "exttable": "extended_2016",
        "subid": 4311334,
        "motion": "1",
        "confidence": "3",
        "asleep": "no",
        "cityid": 73034,
        "region": "cus",
        "orig_id": "us10004vu6",
        "version": "1.4",
        "citydb": "zip_2008",
        "longitude": -97.4165,
        "eventid": "us10004vu6",
        "usertime": "1457356909",
        "latitude": 35.7086,
        "user_cdi": "2.2"
    },
    {
        "dist": 3.2,
        "geo_source": "raw",
        "felt": "1",
        "time_now": "2016-03-07T22:12:35",
        "exttable": "extended_2016",
        "subid": 4311341,
        "confidence": "3",
        "orig_id": "us10004vu6",
        "cityid": 73034,
        "region": "cus",
        "user_cdi": "2.0",
        "version": "1.4",
        "citydb": "zip_2008",
        "eventid": "us10004vu6",
        "usertime": "1457356909",
        "latitude": 35.6812,
        "longitude": -97.425
    }
]