[
    {
        "shelf": "0",
        "picture": "0",
        "reaction": "1",
        "time_now": "2014-06-24T14:54:57",
        "heavy_appliance": "0",
        "exttable": "extended_2014",
        "subid": 3874236,
        "motion": "1",
        "asleep": "no",
        "stand": "0",
        "citydb": "zip_2008",
        "longitude": -97.029,
        "creak": "1 slight",
        "d_text": "_none",
        "latitude": 36.156,
        "eventid": "usc000rl5d",
        "dist": 71.9,
        "walls": "0",
        "felt": "1 yes",
        "version": "1.2",
        "duration": "1",
        "cityid": 74075,
        "confidence": "4",
        "geo_source": "raw",
        "orig_id": "unknown",
        "sway": "0",
        "region": "cus",
        "usertime": "6/24/2014 9:51 AM",
        "furniture": "0",
        "user_cdi": "2.2"
    },
    {
        "shelf": "0 rattled_sligh",
        "picture": "0",
        "reaction": "3",
        "time_now": "2014-06-24T15:05:40",
        "heavy_appliance": "0",
        "exttable": "extended_2014",
        "subid": 3874237,
        "motion": "2",
        "asleep": "no",
        "stand": "0",
        "citydb": "zip_2008",
        "longitude": -97.0,
        "other_felt": "4",
        "creak": "1 loud",
        "d_text": "_none",
        "latitude": 36.1,
        "eventid": "usc000rl5d",
        "dist": 78.1,
        "walls": "0",
        "felt": "1 yes",
        "version": "1.2",
        "duration": "1-2 seconds",
        "cityid": 74074,
        "confidence": "1",
        "geo_source": "raw",
        "user_cdi": "3.4",
        "sway": "0",
        "region": "cus",
        "furniture": "0",
        "orig_id": "usc000rkub"
    },
    {
        "shelf": "0",
        "picture": "0",
        "reaction": "1",
        "time_now": "2014-06-24T15:08:43",
        "heavy_appliance": "0",
        "exttable": "extended_2014",
        "subid": 3874238,
        "motion": "2",
        "asleep": "no",
        "stand": "0",
        "citydb": "zip_2008",
        "longitude": -97.0,
        "other_felt": "4",
        "creak": "1 slight",
        "d_text": "_none",
        "latitude": 36.1,
        "eventid": "usc000rl5d",
        "dist": 78.1,
        "walls": "0",
        "felt": "1 yes",
        "version": "1.2",
        "duration": "1-2 seconds",
        "cityid": 74074,
        "confidence": "1",
        "geo_source": "raw",
        "user_cdi": "2.7",
        "sway": "0",
        "region": "cus",
        "furniture": "0",
        "orig_id": "usc000rl4t"
    },
    {
        "shelf": "0",
        "picture": "0",
        "reaction": "1",
        "time_now": "2014-06-24T15:11:30",
        "heavy_appliance": "0",
        "exttable": "extended_2014",
        "subid": 3874239,
        "motion": "1",
        "stand": "0",
        "citydb": "zip_2008",
        "longitude": -97.0,
        "other_felt": "4",
        "creak": "1 slight",
        "d_text": "_none",
        "latitude": 36.1,
        "eventid": "usc000rl5d",
        "dist": 78.1,
        "walls": "0",
        "felt": "1 yes",
        "version": "1.2",
        "duration": "1-2 seconds",
        "cityid": 74074,
        "confidence": "1",
        "geo_source": "raw",
        "user_cdi": "2.2",
        "sway": "0",
        "region": "cus",
        "furniture": "0",
        "orig_id": "usc000rkb9"
    },
    {
        "shelf": "0",
        "picture": "0",
        "reaction": "1",
        "time_now": "2014-06-24T15:14:28",
        "heavy_appliance": "0",
        "exttable": "extended_2014",
        "subid": 3874240,
        "motion": "1",
        "asleep": "no",
        "stand": "0",
        "citydb": "zip_2008",
        "longitude": -97.0,
        "other_felt": "4",
        "creak": "1 slight",
        "d_text": "_none",
        "latitude": 36.1,
        "eventid": "usc000rl5d",
        "dist": 78.1,
        "walls": "0",
        "felt": "1 yes",
        "version": "1.2",
        "duration": "1-2 seconds",
        "cityid": 74074,
        "confidence": "1",
        "geo_source": "raw",
        "user_cdi": "2.2",
        "sway": "0",
        "region": "cus",
        "furniture": "0",
        "orig_id": "usc000rl54"
    }
]