[
    {
        "shelf": "0 rattled_sligh",
        "picture": "1 did_not_fall",
        "reaction": "1",
        "time_now": "2014-09-14T12:29:26",
        "heavy_appliance": "0",
        "exttable": "extended_2014",
        "subid": 3954342,
        "motion": "2",
        "asleep": "no",
        "stand": "0",
        "citydb": "zip_2008",
        "longitude": -97.868,
        "other_felt": "5",
        "creak": "1 slight",
        "d_text": "_none",
        "latitude": 36.3988,
        "eventid": "usb000sc9y",
        "dist": 27.5,
        "walls": "0",
        "felt": "0 no",
        "version": "1.2",
        "duration": "5-6 seconds",
        "cityid": 73701,
        "confidence": "5",
        "geo_source": "raw",
        "user_cdi": "3.4",
        "sway": "0",
        "region": "cus",
        "furniture": "0",
        "orig_id": "usb000sc9y"
    },
    {
        "shelf": "0 rattled_sligh",
        "picture": "0",
        "reaction": "2",
        "time_now": "2014-09-14T12:33:11",
        "heavy_appliance": "0",
        "exttable": "extended_2014",
        "subid": 3954343,
        "motion": "1",
        "asleep": "no",
        "stand": "0",
        "citydb": "zip_2008",
        "longitude": -98.1,
        "other_felt": "5",
        "creak": "1 slight",
        "d_text": "_none",
        "latitude": 36.4,
        "eventid": "usb000sc9y",
        "dist": 27.6,
        "walls": "0",
        "felt": "1 yes",
        "version": "1.2",
        "duration": "1",
        "cityid": 73754,
        "confidence": "1",
        "geo_source": "raw",
        "user_cdi": "2.7",
        "sway": "0",
        "region": "cus",
        "furniture": "0",
        "orig_id": "usb000sc9y"
    },
    {
        "shelf": "0 rattled_sligh",
        "picture": "0",
        "reaction": "2",
        "time_now": "2014-09-14T12:34:07",
        "heavy_appliance": "0",
        "exttable": "extended_2014",
        "subid": 3954344,
        "motion": "2",
        "asleep": "no",
        "stand": "0",
        "citydb": "zip_2008",
        "longitude": -97.9475,
        "other_felt": "3",
        "creak": "1 slight",
        "d_text": "_none",
        "latitude": 36.6145,
        "eventid": "usb000sc9y",
        "dist": 3.5,
        "walls": "0",
        "felt": "1 yes",
        "version": "1.2",
        "duration": "4",
        "suspect": "4",
        "cityid": 73766,
        "confidence": "-1",
        "geo_source": "raw",
        "user_cdi": "2.5",
        "sway": "0",
        "region": "cus",
        "furniture": "0",
        "orig_id": "usb000sc9y"
    },
    {
        "shelf": "0",
        "picture": "0",
        "reaction": "2",
        "time_now": "2014-09-14T12:39:05",
        "heavy_appliance": "0",
        "exttable": "extended_2014",
        "subid": 3954345,
        "motion": "1",
        "asleep": "woke",
        "stand": "0",
        "citydb": "zip_2008",
        "longitude": -97.9341,
        "other_felt": "2",
        "creak": "1 slight",
        "d_text": "_none",
        "latitude": 36.408,
        "eventid": "usb000sc9y",
        "dist": 24.9,
        "walls": "0",
        "felt": "1 yes",
        "version": "1.2",
        "duration": "10 seconds",
        "cityid": 73703,
        "confidence": "5",
        "geo_source": "raw",
        "user_cdi": "2.0",
        "sway": "0",
        "region": "cus",
        "furniture": "0",
        "orig_id": "usb000sc9y"
    },
    {
        "reaction": "1",
        "time_now": "2014-09-14T12:43:17",
        "exttable": "extended_2014",
        "subid": 3954346,
        "motion": "1",
        "asleep": "no",
        "region": "cus",
        "longitude": -97.8506,
        "d_text": "_none",
        "country": "United States of America",
        "latitude": 36.4068,
        "eventid": "usb000sc9y",
        "dist": 27.3,
        "location": "73701",
        "city": "Enid",
        "felt": "1 yes",
        "version": "1.2",
        "zip": "73701",
        "duration": "6",
        "admin_region": "OK",
        "cityid": 73701,
        "confidence": "4",
        "user_cdi": "2.2",
        "sway": "1 slight",
        "citydb": "zip_2008",
        "geo_source": "raw",
        "orig_id": "usb000sc9y"
    },
    {
        "shelf": "0",
        "picture": "0",
        "reaction": "0",
        "time_now": "2014-09-14T22:54:12",
        "heavy_appliance": "0",
        "exttable": "extended_2014",
        "subid": 3954550,
        "motion": "0",
        "asleep": "slept",
        "stand": "0",
        "region": "cus",
        "longitude": -98.4,
        "other_felt": "2",
        "creak": "0",
        "d_text": "_none",
        "country": "United States of America",
        "latitude": 34.6,
        "eventid": "usb000sc9y",
        "dist": 228.8,
        "location": "73501",
        "city": "Lawton",
        "citydb": "zip_2008",
        "felt": "0 no",
        "version": "1.2",
        "zip": "73501",
        "confidence": "1",
        "admin_region": "OK",
        "cityid": 73501,
        "geo_source": "raw",
        "user_cdi": "1.0",
        "sway": "0",
        "walls": "0",
        "furniture": "0",
        "orig_id": "usb000sc9y"
    },
    {
        "shelf": "0 rattled_sligh",
        "picture": "0",
        "reaction": "1",
        "time_now": "2014-09-15T02:48:28",
        "heavy_appliance": "0",
        "exttable": "extended_2014",
        "subid": 3954596,
        "motion": "1",
        "asleep": "no",
        "stand": "0",
        "citydb": "zip_2008",
        "longitude": -98.086,
        "other_felt": "3",
        "creak": "0",
        "d_text": "_none",
        "latitude": 36.638,
        "eventid": "usb000sc9y",
        "dist": 9.4,
        "walls": "0",
        "felt": "1 yes",
        "version": "1.2",
        "duration": "5",
        "cityid": 73761,
        "confidence": "3",
        "geo_source": "raw",
        "user_cdi": "2.0",
        "sway": "0",
        "region": "cus",
        "furniture": "0",
        "orig_id": "usb000sc9y"
    }
]